lambda_wsgi/__init__.py
lambda_wsgi-0.0.2.dist-info/LICENSE
lambda_wsgi-0.0.2.dist-info/METADATA
lambda_wsgi-0.0.2.dist-info/WHEEL
lambda_wsgi-0.0.2.dist-info/top_level.txt
lambda_wsgi-0.0.2.dist-info/RECORD
